funt/__init__.py
funt/app.py
funt/main.py
funt/model.py
funt/tools.py
funt/views.py
funt_assignment1-0.0.6.dist-info/LICENSE
funt_assignment1-0.0.6.dist-info/METADATA
funt_assignment1-0.0.6.dist-info/WHEEL
funt_assignment1-0.0.6.dist-info/top_level.txt
funt_assignment1-0.0.6.dist-info/RECORD
